CHANGELOG.txt
LICENSE.txt
MANIFEST.in
README.txt
__init__.py
setup.py
test.py
owopy.egg-info/PKG-INFO
owopy.egg-info/SOURCES.txt
owopy.egg-info/dependency_links.txt
owopy.egg-info/top_level.txt