Metadata-Version: 1.1
Name: owopy
Version: 0.0.1
Summary: This module OwOifies your sentences (turns your sentences into japanese "furry" baby babblespeak :>)
Home-page: https://github.com/Nimboss2411/OwOpy
Author: Nimit Grover
Author-email: nimbossthegreat@gmail.com
License: MIT
Keywords: text
Platform: UNKNOWN
Classifier: Development Status :: 5 - Production/Stable
Classifier: Intended Audience :: Other Audience
Classifier: Operating System :: Microsoft :: Windows :: Windows 10
Classifier: License :: OSI Approved :: MIT License
Classifier: Programming Language :: Python :: 3.9
